ninjalib.py
ninjalib-0.0.29.dist-info/licenses/LICENSE
ninjalib-0.0.29.dist-info/METADATA
ninjalib-0.0.29.dist-info/WHEEL
ninjalib-0.0.29.dist-info/top_level.txt
ninjalib-0.0.29.dist-info/RECORD
