Metadata-Version: 2.4
Name: ninjalib
Version: 0.0.29
Summary: ninjalib is a data science library
Author: Invizabel
Project-URL: Homepage, https://github.com/Invizabel/ninjalib
Project-URL: Bug Tracker, https://github.com/Invizabel/ninjalib/issues
Classifier: Programming Language :: Python :: 3
Classifier: License :: OSI Approved :: MIT License
Classifier: Operating System :: OS Independent
Requires-Python: >=3.7
License-File: LICENSE
Dynamic: license-file
